{
    "exercicios": [
        {
            "grupoMuscular": "Peito e Tríceps",
            "nome": "LOCAL !! TRÍCEPS UNIL.CRUZADO",
            "repeticoes": "3 X 20",
            "carga": "Carga Máxima",
            "orientacoes": [],
            "videoId": "sFM-PzhijMU",
            "image": "https://user-images.githubusercontent.com/66516553/209981951-792dbcd4-1cb2-4d69-96fb-c1aec1c2cfa1.png"
        },
        {
            "grupoMuscular": "Peito e Tríceps",
            "nome": "TRÍCEPS FRANCÊS CORDA",
            "repeticoes": "3 X 15",
            "carga": "Carga Máxima",
            "orientacoes": [],
            "videoId": "Otc5BgXa-l8",
            "image": "https://user-images.githubusercontent.com/66516553/209981226-15426e08-8900-4777-8664-2cf988e6ce46.png"
        },
        {
            "grupoMuscular": "Peito e Tríceps",
            "nome": "TRÍCEPS PRONADO + SUPINADO",
            "repeticoes": "3 X 10 pronado + 10 supinado",
            "carga": "aumentando aem cada série",
            "orientacoes": [],
            "videoId": "i8awVst0IZ0",
            "image": "https://user-images.githubusercontent.com/66516553/209980698-73fc24ee-9bcc-40de-8078-1737cc663570.png"
        },
        {
            "grupoMuscular": "Peito e Tríceps",
            "nome": "TRÍCEPS TESTA 2 PEGADAS",
            "repeticoes": "3x12",
            "carga": "aumentando aem cada série",
            "orientacoes": [],
            "videoId": "oqob5MHbzBc",
            "image": "https://user-images.githubusercontent.com/66516553/209980285-5f223d74-9f15-4dd3-82f5-1fe22f519f95.png"
        },
        {
            "grupoMuscular": "Peito e Tríceps",
            "nome": "PEITO NO CROSS",
            "repeticoes": "3x12",
            "carga": "máximo",
            "orientacoes": [],
            "videoId": "o90Pm6qTeNI",
            "image": "https://user-images.githubusercontent.com/66516553/209979756-d050283a-4a80-4353-a2ed-c499384d7da7.png"
        },
        {
            "grupoMuscular": "Peito e Tríceps",
            "nome": "SUPINO 45°",
            "repeticoes": "3x12",
            "carga": "máximo",
            "orientacoes": [],
            "videoId": "oZjIQN0YMX0",
            "image": "https://user-images.githubusercontent.com/66516553/209978739-0b22822e-60c3-48a1-960f-495805e24920.png"
        },
        {
            "grupoMuscular": "Peito e Tríceps",
            "nome": "SUPINO RETO",
            "repeticoes": "1X15 1X12 1X10 1X8 1X6",
            "carga": "máximo e vai diminuindo",
            "orientacoes": [],
            "videoId": "rGc9PbmLUY4",
            "image": "https://user-images.githubusercontent.com/66516553/209474069-38b92555-b6e5-43ea-8210-956b8d15c6c7.png"
        },
        {
            "grupoMuscular": "Peito e Tríceps",
            "nome": "CRUCIFIXO HORIZONTAL NEUTRO",
            "repeticoes": "3 X 10",
            "carga": "máximo",
            "orientacoes": [],
            "videoId": "O_FwRxa-hJo",
            "image": "https://user-images.githubusercontent.com/66516553/209474109-60ec9b0d-2ea0-494d-a644-f103b2b7335f.png"
        },
        {
            "grupoMuscular": "Pernas",
            "nome": "AGACH.SQUAT",
            "repeticoes": "4 X 10",
            "carga": "aumentar",
            "orientacoes": [],
            "videoId": "pc9tkM2mVAs",
            "image": "https://user-images.githubusercontent.com/66516553/209880415-2b900ddc-1986-485e-acc6-144350008f32.png"
        },
        {
            "grupoMuscular": "Bíceps e Costas",
            "nome": "PUXADA TRIANGULO",
            "repeticoes": "1X15 1X12 1X10 1X8 1X6",
            "carga": "aumentar",
            "orientacoes": [],
            "videoId": "qW3-gblri0g",
            "image": "https://user-images.githubusercontent.com/66516553/209880520-5abf2e1d-b7dc-4b33-a508-f55e1b20bdee.png"
        },
        {
            "grupoMuscular": "Ombros",
            "nome": "DESENVOL.ARTICULADO 2pegadas",
            "repeticoes": "3 X 10",
            "carga": "sem exagerar",
            "orientacoes": [
                "Regular banco para joelho fazer 90 graus",
                "Pés na largura do quadril",
                "Curvatura da lombar levemente arqueada.",
                "Apoiar as costas no encosto do banco."
            ],
            "videoId": "k0gD4uBjayA",
            "image": "https://user-images.githubusercontent.com/66516553/209880346-a25bc0b9-f1be-4961-8420-f2a75112993e.png"
        },
        {
            "grupoMuscular": "Ombros",
            "nome": "DESENV.ARNOLD",
            "repeticoes": "1X12 1X10 1X8 1X6",
            "carga": "AUMENTAR o peso entre as repetições",
            "orientacoes": [
                "Banco RETO com encosto para as costas",
                "O antebraço dev ficar na posição vertical no início"
            ],
            "videoId": "YghvTx_GI2c",
            "image": "https://user-images.githubusercontent.com/66516553/210132797-a5ae680c-d6a0-45d5-babd-9b1f530b1f82.png"
        },
        {
            "grupoMuscular": "Ombros",
            "nome": "ELEVAÇÃO LATERAL com drop-set",
            "repeticoes": "3X 8+10+12",
            "carga": "DIMINUIR o peso entre as falhas",
            "orientacoes": [
                "Separe e organize as três duplas de pesos",
                "Não descanse entre as falhas",
                "Ombros para baixo (não contraídos p cima)",
                "Escápulas travadas para tras",
                "Cotovelo não ultrapassa altura do ombro",
                "Punho pouco abaixo do cotovelo no movimento"    
            ],
            "videoId": "A9pbIZp8yZ4",
            "image": "https://user-images.githubusercontent.com/66516553/210133492-1c05559d-0a96-47db-a8a3-e619ce7659cf.png"
        },
        {
            "grupoMuscular": "Ombros",
            "nome": "ELEVA. LATERAL CROSS",
            "repeticoes": "3 X 10",
            "carga": "Aumentar a carga entre as repetições",
            "orientacoes": [
                "Cotovelos e joelhos semi-flexionados",
                "Escápula travada",
                "Sempre executado de forma lenta",
                "Subir até altura do ombro"
            ],
            "videoId": "zZOaVUg9eZ0",
            "image": "https://user-images.githubusercontent.com/66516553/210133775-246d98cb-25c6-42e7-b096-f9dae761020c.png"
        },
        {
            "grupoMuscular": "Ombros",
            "nome": "ELEVA.LATERAL ARTICULADA",
            "repeticoes": "3 X 6²+6",
            "carga": "Conforme suportar - Isomeria",
            "orientacoes": [
                "Faz 6 segurando 2seg no pico + 6 comuns",
                "Máquina da galinha pintadinha"
            ],
            "videoId": "7baYE_O30tY",
            "image": "https://user-images.githubusercontent.com/66516553/210134326-b40b0e2c-ba2c-4a14-a921-5109df4542f9.png"
        },
        {
            "grupoMuscular": "Ombros",
            "nome": "ELEVAÇÃO FRONTAL ALTERNADA",
            "repeticoes": "3 X 10",
            "carga": "AUMENTAR o peso entre as repetições",
            "orientacoes": [
                "Cotovelo alinhado com ombro.",
                "Escápula travada",
                "Subir até altura do ombro",
                "Movimento deve ser lento e controlado"
            ],
            "videoId": "OCYdQ3hQQI4",
            "image": "https://user-images.githubusercontent.com/66516553/210152162-4cf9470a-c11a-416c-9fd0-10fd0d4f1766.png"
        },
        {
            "grupoMuscular": "Ombros",
            "nome": "ELEVA.SUPINADA BARRA",
            "repeticoes": "3 X 10",
            "carga": "AUMENTAR o peso entre as repetições",
            "orientacoes": [
                "A palma da mão fica para cima.",
                "Elevar até alçtura do peito",
                "Estabilize o corpo pondo um pé a frente do outro."
                ],
            "videoId": "PGGNQibvra8",
            "image": "https://user-images.githubusercontent.com/66516553/210134737-58d18aa6-ffa7-40be-a47a-f585275375c1.png"
        },
        {
            "grupoMuscular": "Ombros",
            "nome": "REMADA  ALTA",
            "repeticoes": "3X 10+10+10",
            "carga": "Aumenta em cada bloco de 10",
            "orientacoes": [
                "Pode ser no cross ou com alteres (lesiona menos o ombro)",
                "Subir até altura do queixo"
                ],
            "videoId": "qVdQsMODm0o",
            "image": "https://user-images.githubusercontent.com/66516553/210135359-6a3b60b3-6b9e-4a69-8b13-e1b343b21f88.png"
        },
        {
            "grupoMuscular": "Ombros",
            "nome": "ENCOL. OMBROS CROSS",
            "repeticoes": "3 X 20",
            "carga": "Aumentar a cada série",
            "orientacoes": [
                "Deve ser uma pegada aberta."
                ],
            "videoId": "sX92Wnff5R4",
            "image": "https://user-images.githubusercontent.com/66516553/210135909-0d0dc1e4-838b-409d-b781-a28882eb531c.png"
        },
        {
            "grupoMuscular": "Ombros",
            "nome": "ELEV. LATERAL NEUTRA CROSS",
            "repeticoes": "3 X 10",
            "carga": "Conforme suportar",
            "orientacoes": [
                "Confirmar a direção do polegar."
                ],
            "videoId": "YkVfVtGUSAM",
            "image": "https://user-images.githubusercontent.com/66516553/210136214-de47a54a-5566-435c-a214-b6df5b17a761.png"
        }
    ]
}